HISTORY.md
Makefile
README.md
djaxei/__init__.py
djaxei/actions.py
djaxei/admin.py
djaxei/apps.py
djaxei/exceptions.py
djaxei/exp.py
djaxei/imp.py
djaxei/migrations/__init__.py
djaxei/models.py
djaxei/providers/__init__.py
djaxei/providers/xlsxwriter_provider.py
djaxei/providers/xlwt_provider.py
djaxei/templates/djaxei/replace_with_xls.html
djaxei/tests.py
djaxei/views.py
djaxei-0.7.0.dist-info/LICENSE.txt
djaxei-0.7.0.dist-info/WHEEL
djaxei-0.7.0.dist-info/METADATA
djaxei-0.7.0.dist-info/RECORD
