Metadata-Version: 2.1
Name: djaxei
Version: 0.7.0
Summary: A django admin extension for importing exporting records from/to xls/ods
Home-page: https://github.com/GigiusB/djaxei.git
License: MIT
Keywords: xls
Author: Giovanni Bronzini
Author-email: g.bronzini@gmail.com
Requires-Python: >=3.6.1,<4
Classifier: License :: OSI Approved :: MIT License
Classifier: Programming Language :: Python :: 3
Classifier: Programming Language :: Python :: 3.7
Classifier: Programming Language :: Python :: 3.8
Classifier: Programming Language :: Python :: 3.9
Provides-Extra: openpyxl
Provides-Extra: xlsxwriter
Provides-Extra: xlwt
Requires-Dist: django (>=1.11,<4)
Requires-Dist: openpyxl (<4); extra == "openpyxl"
Requires-Dist: xlsxwriter (>=1.2.8); extra == "xlsxwriter"
Requires-Dist: xlwt (>=1.2.0); extra == "xlwt"
Project-URL: Repository, https://github.com/GigiusB/djaxei.git
